[{
    "id": 1,
    "author": "我在乎你在乎的在乎",
    "header": "【今日囧图】说什么也不肯扔了这个陪了他十年的抱枕，不知道为什么",
    "time":"昨天 22时24分",
    "title": "“中国有嘻哈”恶搞视频“台湾有嘻哈”最新更新！！",
    "read": 122119,
    "reply": 1254,
    "like": 6379,
    "image": "../../static/images/yule.gif",
    "desc":"倩倩，我感觉我男朋友最近好像出轨了"
}, {
    "id": 2,
    "author": "会计~~",
    "header": "0-30！这是足球比分 巴西青年队狂进30球胜中国球队",
    "time": "昨天 18时36分",
    "title": "隔着屏幕都能感受到那股绝望与无助~",
    "read": 39000,
    "reply": 374,
    "like": 1483,
    "image": "../../static/images/yule5.gif",
     "desc":"0-30！这是足球比分 巴西青年队狂进30球胜中国。"

}, {
    "id": 3,
    "author": "今天有小雨",
    "header": "女子被狗咬按时打针仍死亡 丈夫:为何疫苗没用",
    "title": "大粗腿，变身细长直！美腿专题开启",
     "time": "昨天 18时24分",
    "read": 15783,
    "reply": 89,
    "like": 1180,
    "image": "../../static/images/yule1.jpg",
     "desc":"物流大战再升级 ：百世、圆通被京东相继“封杀”后发"
}, {
    "id": 4,
    "author": "哥特式的华丽",
    "header": "Ac囧图Vol.369：上街看白丝好不好",
    "time": "昨天 20时25分",
    "title": "【意大利烤牛肉】意大利的一个集市上用巨大烧烤架烤牛肉肋骨",
    "read": 25718,
    "reply": 286,
    "like": 777,
    "image": "../../static/images/yule3.png",
     "desc":"囧图合辑 http://www.acfun.cn/"
}, {
    "id": 5,
    "author": "紫色秋枫",
    "header": "日本男孩爱穿女装成网红 称没谈过恋爱",
    "title": "【奥雷】国产高分剧情片《盲井》速看",
    "read": 16772,
    "reply": 183,
    "like": 608,
    "image": "../../static/images/yule6.jpg",
     "desc":"日本男孩爱穿女装成网红 称没谈过恋爱"
},
{
    "id": 6,
    "author": "独角丘比猫",
    "header": "凌晨时分男子“试手气”开后备箱 竟盗得6瓶茅台5条1916香烟",
    "title": "【萌到你全身酥软的汪星人】可爱萌宠狗狗..........",
    "read": 16772,
    "reply": 183,
    "like": 985,
    "image": "../../static/images/yule7.png",
     "desc":"香港流感疫情严峻 两个月累计致240死"
}


]
